setup.py
fmax/__init__.py
fmax/email.py
fmax/fib.py
fmax/fm.py
ljf7_max.egg-info/PKG-INFO
ljf7_max.egg-info/SOURCES.txt
ljf7_max.egg-info/dependency_links.txt
ljf7_max.egg-info/top_level.txt