Metadata-Version: 2.1
Name: ljf7-max
Version: 171
Summary: To solve fib by recursion and count max frequency
Author: Andy Woz
